emoji_toolchain/commands.py
emoji_toolchain/emojis.py
sleepyemoji.py
sleepyemoji-3.8.5.dist-info/LICENSE
sleepyemoji-3.8.5.dist-info/METADATA
sleepyemoji-3.8.5.dist-info/WHEEL
sleepyemoji-3.8.5.dist-info/RECORD
