Metadata-Version: 2.1
Name: sleepyemoji
Version: 3.8.5
Summary: Print all the emojis that sleepyboy thinks are worthwhile!
Home-page: https://github.com/anthonybench/emoji
License: GNU GPL
Keywords: emoji,unicode
Author: anthonybench
Author-email: anythonybenchyep@gmail.com
Requires-Python: >=3.10,<4.0
Classifier: License :: Other/Proprietary License
Classifier: Programming Language :: Python :: 3
Classifier: Programming Language :: Python :: 3.10
Classifier: Programming Language :: Python :: 3.11
Requires-Dist: prettytable (>=3.8,<4.0)
Requires-Dist: typer (>=0.9,<0.10)
Project-URL: Repository, https://github.com/anthonybench/emoji
